{
  "fetch_stats": {
    "total_accounts": 7,
    "success_count": 6,
    "failed_count": 8,
    "total_cost": 3.0
  },
  "fetch_time": "2025-09-15T15:10:39.607836",
  "account_info": [
    {
      "name": "高瞻的論正人生",
      "biz": "Mzk4ODQzMTM3NA==",
      "category_id": "politics",
      "category_name": "论正人生",
      "principal_info": {
        "wx_id": "gh_3b901079a4d0",
        "owner_name": "个人",
        "registered_id": "",
        "verify_status": "未认证",
        "desc": "论天下之道，守万世之正。不随波逐流，不媚俗妥协，于时代纷争中发出清正之声。",
        "service_phone": "",
        "last_login_country": "中国",
        "last_login_province": "中国香港"
      },
      "basic_info": null,
      "fetch_time": "2025-09-15T15:09:49.025327",
      "total_cost": 1.0
    },
    {
      "name": "高瞻的智慧人生",
      "biz": "MzkwNDg1MzEwMg==",
      "category_id": "wisdom",
      "category_name": "智慧人生",
      "principal_info": {
        "change_info_list": [],
        "reg_time": "2024-10-25",
        "reg_time_stamp": 1729785600,
        "registered_id": "",
        "auth_3rd_list": [],
        "verify_customer_type": "未认证",
        "gh_id": "gh_cbc799f95a00",
        "customer_type": "个人",
        "registered_country": "中国",
        "is_overseas": 0,
        "company_name": "个人",
        "province": null,
        "gender": "女",
        "wx_id": "sgsealong",
        "owner_name": "个人",
        "verify_status": "未认证",
        "desc": "这里没有空洞的说教，只有深邃的思想；没有浮躁的繁华，只有璀璨的智慧。",
        "service_phone": "",
        "last_login_country": "新加坡",
        "last_login_province": ""
      },
      "basic_info": null,
      "fetch_time": "2025-09-15T15:10:00.637229",
      "total_cost": 1.0
    },
    {
      "name": "高瞻的交易人生",
      "biz": "MzkxNzgzNTEwNQ==",
      "category_id": "trading",
      "category_name": "交易人生",
      "principal_info": {
        "change_info_list": [],
        "reg_time": "2024-10-18",
        "reg_time_stamp": 1729180800,
        "registered_id": "",
        "auth_3rd_list": [],
        "verify_customer_type": "未认证",
        "gh_id": "gh_d0d12c149820",
        "customer_type": "个人",
        "registered_country": "中国",
        "is_overseas": 0,
        "company_name": "个人",
        "province": "四川省",
        "gender": "女",
        "wx_id": "nlsealoong",
        "owner_name": "个人",
        "verify_status": "未认证",
        "desc": "投机展现智慧，交易改变未来。",
        "service_phone": "",
        "last_login_country": "新加坡",
        "last_login_province": ""
      },
      "basic_info": null,
      "fetch_time": "2025-09-15T15:10:05.312450",
      "total_cost": 1.0
    },
    {
      "name": "高瞻的文艺人生",
      "biz": "Mzk0Mjg1MzQ1NA==",
      "category_id": "literary",
      "category_name": "文艺人生",
      "principal_info": {
        "change_info_list": [],
        "reg_time": "2024-10-25",
        "reg_time_stamp": 1729785600,
        "registered_id": "",
        "auth_3rd_list": [],
        "verify_customer_type": "未认证",
        "gh_id": "gh_40cb1f9feddd",
        "customer_type": "个人",
        "registered_country": "中国",
        "is_overseas": 0,
        "company_name": "个人",
        "province": "江苏省",
        "gender": "男"
      },
      "basic_info": null,
      "fetch_time": "2025-09-15T15:10:10.013976",
      "total_cost": 1.0
    },
    {
      "name": "高瞻的音乐人生",
      "biz": "MzE5OTMxOTg3OQ==",
      "category_id": "music",
      "category_name": "音乐人生",
      "principal_info": {
        "change_info_list": [],
        "reg_time": "2025-08-16",
        "reg_time_stamp": 1755273600,
        "registered_id": "",
        "auth_3rd_list": [],
        "verify_customer_type": "未认证",
        "gh_id": "gh_9da090971b28",
        "customer_type": "个人",
        "registered_country": "中国",
        "is_overseas": 0,
        "company_name": "个人",
        "province": null,
        "gender": "女"
      },
      "basic_info": null,
      "fetch_time": "2025-09-15T15:10:20.357405",
      "total_cost": 1.0
    },
    {
      "name": "高瞻的咨询人生",
      "biz": "Mzk1NzI0NDY4MQ==",
      "category_id": "consulting",
      "category_name": "咨询人生",
      "principal_info": null,
      "basic_info": null,
      "fetch_time": "2025-09-15T15:10:30.804165",
      "total_cost": 1.0
    },
    {
      "name": "高瞻的术数人生",
      "biz": "MzkzODkzNTE2Mg==",
      "category_id": "numerology",
      "category_name": "术数人生",
      "principal_info": {
        "change_info_list": [],
        "reg_time": "2025-03-24",
        "reg_time_stamp": 1742745600,
        "registered_id": "",
        "auth_3rd_list": [],
        "verify_customer_type": "未认证",
        "gh_id": "gh_7b5a131889b3",
        "customer_type": "个人",
        "registered_country": "中国",
        "is_overseas": 0,
        "company_name": "个人",
        "province": "四川省",
        "gender": "男",
        "wx_id": "gh_7b5a131889b3",
        "owner_name": "个人",
        "verify_status": "未认证",
        "desc": "圣人不器，君子通道，止于术数。",
        "service_phone": "",
        "last_login_country": "新加坡",
        "last_login_province": ""
      },
      "basic_info": null,
      "fetch_time": "2025-09-15T15:10:34.928838",
      "total_cost": 1.0
    }
  ]
}